api_seiketsu/__init__.py
api_seiketsu/api_seiketsu.py
api_seiketsu/api_seiketsu_image.py
api_seiketsu/data/firebase_credentials.json
seiketsu_api-1.6.0.dist-info/METADATA
seiketsu_api-1.6.0.dist-info/WHEEL
seiketsu_api-1.6.0.dist-info/top_level.txt
seiketsu_api-1.6.0.dist-info/RECORD
