Metadata-Version: 2.1
Name: seiketsu-api
Version: 1.6.0
Summary: A Python library to interact with a chat API
Home-page: https://github.com/yourusername/my-json-package
Author: LoLip_p
Author-email: mr.timon51@gmail.com
Requires-Dist: google-cloud-firestore >=2.11.1
Requires-Dist: google-auth >=2.22.0
Requires-Dist: google-auth-httplib2 >=0.1.0
